{
  "version": "2.1",
  "metadata": {
    "id": "otitis-media",
    "slug": "otitis-media",
    "displayName": "Otitis Media",
    "specialty": "General Practice",
    "triggers": [
      "/otitismedia"
    ]
  },
  "snippets": [
    {
      "id": "otitis-media-hx",
      "trigger": "otitismedia",
      "label": "Otitis Media focused history",
      "category": "History",
      "content": "Focused history for [Duration]. Key symptoms reviewed. Red flags screened and documented."
    },
    {
      "id": "otitis-media-plan",
      "trigger": "otitismediaplan",
      "label": "Otitis Media management plan",
      "category": "Plan",
      "content": "Shared plan agreed. Safety net provided. Follow-up advised based on trajectory and risk."
    }
  ],
  "reasoning": {
    "discriminators": [
      "Otalgia pattern, fever, and hearing change",
      "Otoscopic appearance and tympanic membrane findings",
      "Post-auricular tenderness or swelling",
      "Systemic toxicity or neurological symptoms",
      "Immunocompromise or recurrent episodes"
    ],
    "mustNotMiss": [
      "Mastoiditis",
      "Intracranial infection (meningitis or abscess)",
      "Malignant otitis externa in high-risk patients"
    ],
    "redFlags": [
      "Post-auricular swelling, erythema, or protruding pinna",
      "Severe headache, photophobia, or neck stiffness",
      "Facial nerve weakness or other cranial nerve signs",
      "Persistent high fever with systemic toxicity",
      "Rapidly worsening pain despite treatment"
    ],
    "references": [
      {
        "label": "NICE CKS - Otitis media",
        "url": "https://cks.nice.org.uk/topics/otitis-media-acute/"
      }
    ]
  },
  "structuredFields": [
    {
      "id": "history",
      "title": "History",
      "fields": [
        {
          "id": "duration",
          "label": "Duration",
          "type": "text",
          "placeholder": "e.g., 3 days"
        },
        {
          "id": "severity",
          "label": "Severity",
          "type": "select",
          "options": [
            "mild",
            "moderate",
            "severe"
          ]
        },
        {
          "id": "red-flag-screen",
          "label": "Red flags screened",
          "type": "toggle"
        }
      ]
    },
    {
      "id": "exam",
      "title": "Examination",
      "fields": [
        {
          "id": "focused-exam",
          "label": "Focused exam summary",
          "type": "textarea"
        }
      ]
    },
    {
      "id": "assessment",
      "title": "Assessment",
      "fields": [
        {
          "id": "impression",
          "label": "Impression",
          "type": "textarea"
        }
      ]
    },
    {
      "id": "plan",
      "title": "Plan",
      "fields": [
        {
          "id": "management",
          "label": "Management",
          "type": "textarea"
        },
        {
          "id": "follow-up",
          "label": "Follow-up",
          "type": "text"
        }
      ]
    },
    {
      "id": "safety-net",
      "title": "Safety Net",
      "fields": [
        {
          "id": "safety-advice",
          "label": "Safety net advice given",
          "type": "toggle"
        },
        {
          "id": "safety-details",
          "label": "Safety details",
          "type": "textarea",
          "showIf": "safety-advice == true"
        }
      ]
    }
  ],
  "outputTemplate": {
    "sections": [
      {
        "id": "editor",
        "title": "Clinical Notes",
        "source": "editor",
        "includeByDefault": true
      },
      {
        "id": "history",
        "title": "History",
        "source": "structured",
        "structuredSectionId": "history",
        "includeByDefault": true
      },
      {
        "id": "exam",
        "title": "Examination",
        "source": "structured",
        "structuredSectionId": "exam",
        "includeByDefault": true
      },
      {
        "id": "assessment",
        "title": "Assessment",
        "source": "structured",
        "structuredSectionId": "assessment",
        "includeByDefault": true
      },
      {
        "id": "ddx-assessment",
        "title": "Working Differential",
        "source": "ddx",
        "includeByDefault": true
      },
      {
        "id": "plan",
        "title": "Plan",
        "source": "structured",
        "structuredSectionId": "plan",
        "includeByDefault": true
      },
      {
        "id": "safety-net",
        "title": "Safety Net",
        "source": "structured",
        "structuredSectionId": "safety-net",
        "includeByDefault": true
      }
    ]
  },
  "review": {
    "illnessScript": {
      "summary": "Otitis media assessment in primary care: confirm uncomplicated infection, identify suppurative complications, and provide clear safety-net advice."
    },
    "mustNotMiss": [
      {
        "condition": "Mastoiditis",
        "redFlags": [
          "Post-auricular swelling, erythema, or protruding pinna",
          "Severe headache, photophobia, or neck stiffness",
          "Facial nerve weakness or other cranial nerve signs",
          "Persistent high fever with systemic toxicity",
          "Rapidly worsening pain despite treatment"
        ],
        "whyDangerous": "Can spread intracranially and cause severe complications.",
        "escalationConcern": "Urgent ENT/emergency referral for post-auricular signs or persistent severe pain/fever."
      },
      {
        "condition": "Intracranial infection (meningitis or abscess)",
        "redFlags": [
          "Post-auricular swelling, erythema, or protruding pinna",
          "Severe headache, photophobia, or neck stiffness",
          "Facial nerve weakness or other cranial nerve signs",
          "Persistent high fever with systemic toxicity",
          "Rapidly worsening pain despite treatment"
        ],
        "whyDangerous": "Life-threatening neurological deterioration can occur rapidly.",
        "escalationConcern": "Emergency transfer for neurological symptoms, meningism, or systemic toxicity."
      },
      {
        "condition": "Malignant otitis externa in high-risk patients",
        "redFlags": [
          "Post-auricular swelling, erythema, or protruding pinna",
          "Severe headache, photophobia, or neck stiffness",
          "Facial nerve weakness or other cranial nerve signs",
          "Persistent high fever with systemic toxicity",
          "Rapidly worsening pain despite treatment"
        ],
        "whyDangerous": "Can progress to skull-base osteomyelitis with cranial neuropathies.",
        "escalationConcern": "Urgent specialist assessment for severe refractory otalgia in diabetes/immunosuppression."
      }
    ],
    "discriminators": [
      {
        "question": "Otalgia pattern, fever, and hearing change",
        "reasoning": "Helps prioritize immediate risk while refining the working diagnosis.",
        "clinicalValue": "Improves triage decisions and reduces missed serious disease."
      },
      {
        "question": "Otoscopic appearance and tympanic membrane findings",
        "reasoning": "Helps prioritize immediate risk while refining the working diagnosis.",
        "clinicalValue": "Improves triage decisions and reduces missed serious disease."
      },
      {
        "question": "Post-auricular tenderness or swelling",
        "reasoning": "Helps prioritize immediate risk while refining the working diagnosis.",
        "clinicalValue": "Improves triage decisions and reduces missed serious disease."
      },
      {
        "question": "Systemic toxicity or neurological symptoms",
        "reasoning": "Helps prioritize immediate risk while refining the working diagnosis.",
        "clinicalValue": "Improves triage decisions and reduces missed serious disease."
      },
      {
        "question": "Immunocompromise or recurrent episodes",
        "reasoning": "Helps prioritize immediate risk while refining the working diagnosis.",
        "clinicalValue": "Improves triage decisions and reduces missed serious disease."
      }
    ],
    "historyPrompts": [
      {
        "category": "History",
        "prompts": [
          {
            "id": "hx-duration",
            "label": "Duration",
            "mode": "text",
            "placeholder": "e.g., 3 days"
          },
          {
            "id": "hx-severity",
            "label": "Severity",
            "mode": "text"
          },
          {
            "id": "hx-red-flag-screen",
            "label": "Red flags screened",
            "mode": "text"
          }
        ]
      }
    ],
    "examSections": [
      {
        "id": "exam",
        "title": "Examination",
        "prompts": [
          {
            "id": "ex-focused-exam",
            "label": "Focused exam summary",
            "significance": "Supports narrowing differential and immediate safety decisions."
          }
        ]
      }
    ],
    "diagnoses": {
      "common": [
        {
          "name": "Acute otitis media"
        },
        {
          "name": "Otitis media with effusion"
        },
        {
          "name": "Referred otalgia from upper respiratory infection"
        }
      ],
      "mustNotMiss": [
        {
          "name": "Mastoiditis"
        },
        {
          "name": "Intracranial infection (meningitis or abscess)"
        },
        {
          "name": "Malignant otitis externa in high-risk patients"
        }
      ],
      "oftenMissed": [
        {
          "name": "Otitis externa coexisting with middle-ear symptoms"
        }
      ]
    },
    "investigations": {
      "whenHelpful": [
        {
          "test": "Point-of-care observations",
          "rationale": "Helps detect physiological instability during consultation."
        },
        {
          "test": "Targeted bedside test",
          "rationale": "Used when findings will change immediate management."
        },
        {
          "test": "Selective laboratory test",
          "rationale": "Reserve for diagnostic uncertainty or higher risk presentations."
        }
      ],
      "whenNotNeeded": [],
      "limitations": []
    },
    "managementConsiderations": {
      "selfCare": [
        "Provide symptom-control advice tailored to current severity.",
        "Confirm patient understands red-flag escalation instructions."
      ],
      "pharmacologicalConcepts": [],
      "delayedStrategies": [],
      "followUpLogic": [
        "Escalate immediately for mastoid, intracranial, or cranial nerve complication signs.",
        "Review persistent symptoms or hearing concerns and consider reassessment pathway.",
        "Provide explicit advice for worsening fever, pain, swelling, or neurological features."
      ]
    },
    "safetyNetting": {
      "returnAdvice": [
        "Seek urgent care for worsening pain with swelling behind the ear or pinna displacement.",
        "Seek urgent care for persistent high fever, severe headache, or neck stiffness.",
        "Return if hearing worsens, discharge persists, or symptoms fail to improve."
      ],
      "escalationTriggers": [
        "Post-auricular swelling, erythema, or protruding pinna",
        "Severe headache, photophobia, or neck stiffness",
        "Facial nerve weakness or other cranial nerve signs",
        "Persistent high fever with systemic toxicity",
        "Rapidly worsening pain despite treatment"
      ]
    },
    "mindset": "Balance efficiency with explicit risk documentation."
  },
  "jitl": {
    "termMap": [],
    "linkProviders": [
      {
        "row": 1,
        "label": "Perplexity",
        "hrefTemplate": "https://www.perplexity.ai/search?q=SEARCH_TERM"
      },
      {
        "row": 1,
        "label": "NICE",
        "hrefTemplate": "https://www.google.com/search?q=SEARCH_TERM+site:nice.org.uk"
      },
      {
        "row": 2,
        "label": "CKS",
        "hrefTemplate": "https://www.google.com/search?q=SEARCH_TERM+site:cks.nice.org.uk"
      },
      {
        "row": 2,
        "label": "BNF",
        "hrefTemplate": "https://www.google.com/search?q=SEARCH_TERM+site:bnf.nice.org.uk"
      },
      {
        "row": 3,
        "label": "BMJ",
        "hrefTemplate": "https://www.google.com/search?q=SEARCH_TERM+site:bestpractice.bmj.com"
      },
      {
        "row": 3,
        "label": "Google",
        "hrefTemplate": "https://www.google.com/search?q=SEARCH_TERM"
      }
    ]
  },
  "ddx": {
    "evidencePrompts": [
      "Otalgia pattern, fever, and hearing change",
      "Otoscopic appearance and tympanic membrane findings",
      "Post-auricular tenderness or swelling",
      "Systemic toxicity or neurological symptoms",
      "Immunocompromise or recurrent episodes"
    ],
    "compareEnabled": true
  },
  "qa": {
    "status": "approved",
    "clinicalReviewer": "Pilot Clinical QA",
    "reviewedAt": "2026-02-15",
    "version": "1.0.0"
  }
}
